simpledl/__init__.py
simpledl/utils.py
simple_dl_toolkit-0.0.2.dist-info/LICENSE
simple_dl_toolkit-0.0.2.dist-info/METADATA
simple_dl_toolkit-0.0.2.dist-info/WHEEL
simple_dl_toolkit-0.0.2.dist-info/top_level.txt
simple_dl_toolkit-0.0.2.dist-info/RECORD
