Metadata-Version: 2.1
Name: simple-dl-toolkit
Version: 0.0.2
Summary: Simple deep learning toolkit
Home-page: https://github.com/YongfeiYan/simpledl
Author: Yongfei Yan
Author-email: YongfeiYan <yognfeiyan@pku.edu.cn>
Project-URL: Homepage, https://github.com/YongfeiYan/simpledl
Project-URL: Bug Tracker, https://github.com/YongfeiYan/simpledl/issues
Classifier: Programming Language :: Python :: 3
Classifier: License :: OSI Approved :: MIT License
Classifier: Operating System :: OS Independent
Requires-Python: >=3.6
License-File: LICENSE
